{
  "id": "prologue_prop_and_follow",
  "durationMs": 8000,
  "tracks": [
    {
      "id": "camera.cutscene",
      "kind": "camera",
      "binding": { "cameraId": "scripted" },
      "channel": "frame",
      "clips": [
        { "type": "setCameraFrame", "atMs": 1000, "center": [-1.2, 0, 0], "height": 2.5, "orthoWidth": 20 },
        { "type": "cameraBlend", "startMs": 1000, "durationMs": 1000, "to": "scripted" },
        { "type": "setCameraFrame", "atMs": 3000, "center": [-1, -1, 0], "height": 1, "orthoWidth": 20 },
        { "type": "cameraBlend", "startMs": 3000, "durationMs": 1000, "to": "scripted" },
        { "type": "setCameraFollow", "atMs": 3000, "actorId": "prop_faller", "offsetX": 0, "offsetY": 0, "offsetZ": 0, "lerp": 0.12, "height": 1, "orthoWidth": 20 }
      ]
    },
    {
      "id": "camera.back",
      "kind": "camera",
      "binding": { "cameraId": "explore" },
      "channel": "blend",
      "clips": [
        { "type": "cameraBlend", "startMs": 6500, "durationMs": 1500, "to": "explore" }
      ]
    },
    {
      "id": "prop.idle",
      "kind": "actor",
      "binding": { "actorId": "prop_faller" },
      "channel": "command",
      "clips": [
        { "type": "command", "atMs": 0, "command": "idle" }
      ]
    },
    {
      "id": "prop.fall",
      "kind": "actor",
      "binding": { "actorId": "prop_faller" },
      "channel": "command",
      "clips": [
        { "type": "command", "atMs": 3500, "command": "fall" },
        { "type": "moveActorTo", "startMs": 3500, "durationMs": 400, "x": -1.2, "y": -1.25, "speed": 4 }
      ]
    },
    {
      "id": "prop.land",
      "kind": "actor",
      "binding": { "actorId": "prop_faller" },
      "channel": "command",
      "clips": [
        { "type": "command", "atMs": 3900, "command": "land" }
      ]
    },
    {
      "id": "prop.run",
      "kind": "actor",
      "binding": { "actorId": "prop_faller" },
      "channel": "command",
      "clips": [
        { "type": "command", "atMs": 4200, "command": "run" },
        { "type": "moveActorTo", "startMs": 4200, "durationMs": 3000, "x": 25, "y": 0, "speed": 4 }
      ]
    },
    {
      "id": "prop.dispose",
      "kind": "callback",
      "clips": [
        { "type": "callback", "atMs": 7800, "fn": "disposeProp", "actorId": "prop_faller" }
      ]
    },
    {
      "id": "companion.bubble_show",
      "kind": "callback",
      "binding": { "actorId": "companion" },
      "clips": [
        { "type": "dialogueBubble", "atMs": 800, "actorId": "companion", "text": "!" }
      ]
    },
    {
      "id": "companion.bubble_wait",
      "kind": "wait",
      "clips": [
        { "type": "wait", "atMs": 800, "durationMs": 2000 }
      ]
    },
    {
      "id": "companion.bubble_hide",
      "kind": "callback",
      "clips": [
        { "type": "dialogueBubble", "atMs": 2500, "action": "hide" }
      ]
    },
    {
      "id": "companion.follow",
      "kind": "callback",
      "clips": [
        { "type": "callback", "atMs": 7400, "fn": "enterCompanionFollowing" }
      ]
    },
    {
      "id": "fx.letterbox",
      "kind": "camera",
      "channel": "fx",
      "clips": [
        { "type": "cameraEffect", "atMs": 0, "effect": "letterbox", "durationMs": 6500, "height": 72, "speed": 240 }
      ]
    },{
      "id": "hero.attention",
      "kind": "actor",
      "binding": { "actorId": "hero" },
      "channel": "movement",
      "clips": [
        { "type": "inputLock", "atMs": 0, "locked": true },
        { "type": "command", "atMs": 200, "command": "walk" },
        { "type": "faceWorldX", "atMs": 100, "direction": 1 },
        { "type": "moveActorTo", "startMs": 200, "durationMs": 500, "x": -21.5, "y": 0.4, "speed": 1.4},
        { "type": "inputLock", "atMs": 8000, "locked": false }
      ]
    },
    {
      "id": "companion.attention",
      "kind": "actor",
      "binding": { "actorId": "companion" },
      "channel": "movement",
      "clips": [
          { "type": "command", "atMs": 0, "command": "walk" },
           { "type": "faceWorldX", "atMs": 100, "direction": 1 },
           { "type": "moveActorTo", "startMs": 0, "durationMs": 500, "x": -23.2, "y": 0.4, "speed": 1.4 },
            { "type": "callback", "atMs": 600, "fn": "enterCompanionIdle" }
      ]
    },
    {
      "id": "enemy_1.in_position",
      "kind": "actor",
      "binding": { "actorId": "enemy_1" },
      "channel": "movement",
      "clips": [
          { "type": "command", "atMs": 3700, "command": "move" },
           { "type": "moveActorTo", "startMs": 3700, "durationMs": 1000, "x": -1.2, "y": -0.4, "speed": 1.4 }
      ]
    }
  ]
}